hax/__init__.py
hax/_checks.py
hax/_hax.py
hax/_helpers.py
hax/_test.py
hax-0.3.0.dist-info/LICENSE.md
hax-0.3.0.dist-info/METADATA
hax-0.3.0.dist-info/WHEEL
hax-0.3.0.dist-info/top_level.txt
hax-0.3.0.dist-info/RECORD
