Metadata-Version: 2.1
Name: hax
Version: 0.3.0
Summary: Write compiled bytecode inline with standard Python syntax.
Home-page: https://github.com/brandtbucher/hax
Author: Brandt Bucher
Author-email: brandtbucher@gmail.com
License: MIT
Keywords: bytecode
License-File: LICENSE.md
